vhdl/src/data_memory.vhd
library IEEE;
use IEEE.STD_LOGIC_1164.ALL;
use IEEE.NUMERIC_STD.ALL;

entity Data_Memory is
    Port (
        clk        : in  STD_LOGIC;
        mem_write  : in  STD_LOGIC;
        mem_read   : in  STD_LOGIC;
        address    : in  STD_LOGIC_VECTOR(31 downto 0);
        write_data : in  STD_LOGIC_VECTOR(31 downto 0);
        read_data  : out STD_LOGIC_VECTOR(31 downto 0)
    );
end Data_Memory;

architecture Behavioral of Data_Memory is
    type mem_array is array (0 to 255) of STD_LOGIC_VECTOR(31 downto 0);
    signal memory : mem_array := (others => (others => '0'));
begin

    process(clk)
    begin
        if rising_edge(clk) then
            if mem_write = '1' then
                memory(to_integer(unsigned(address(7 downto 0)))) <= write_data;
            end if;

            if mem_read = '1' then
                read_data <= memory(to_integer(unsigned(address(7 downto 0))));
            else
                read_data <= (others => '0');
            end if;
        end if;
    end process;

end Behavioral;

vhdl/testbench/data_memory_tb.vhd
library IEEE;
use IEEE.STD_LOGIC_1164.ALL;
use IEEE.NUMERIC_STD.ALL;

entity Data_Memory_TB is
end Data_Memory_TB;

architecture Behavioral of Data_Memory_TB is

    component Data_Memory
        Port (
            clk        : in  STD_LOGIC;
            mem_write  : in  STD_LOGIC;
            mem_read   : in  STD_LOGIC;
            address    : in  STD_LOGIC_VECTOR(31 downto 0);
            write_data : in  STD_LOGIC_VECTOR(31 downto 0);
            read_data  : out STD_LOGIC_VECTOR(31 downto 0)
        );
    end component;

    signal clk        : STD_LOGIC := '0';
    signal mem_write  : STD_LOGIC := '0';
    signal mem_read   : STD_LOGIC := '0';
    signal address    : STD_LOGIC_VECTOR(31 downto 0) := (others => '0');
    signal write_data : STD_LOGIC_VECTOR(31 downto 0) := (others => '0');
    signal read_data  : STD_LOGIC_VECTOR(31 downto 0);

begin

    uut: Data_Memory
        port map (
            clk        => clk,
            mem_write  => mem_write,
            mem_read   => mem_read,
            address    => address,
            write_data => write_data,
            read_data  => read_data
        );

    clk_process : process
    begin
        while true loop
            clk <= '0';
            wait for 5 ns;
            clk <= '1';
            wait for 5 ns;
        end loop;
    end process;

    stim_proc : process
    begin
        -- Task 1(i): Write 1024 into Memory Address 2, then read it
        address    <= x"00000002";
        write_data <= std_logic_vector(to_unsigned(1024, 32));
        mem_write  <= '1';
        mem_read   <= '0';
        wait for 10 ns;

        mem_write  <= '0';
        mem_read   <= '1';
        wait for 10 ns;
        assert read_data = std_logic_vector(to_unsigned(1024, 32))
            report "Task 1(i) readback mismatch at address 2"
            severity error;

        -- Task 1(ii): Write 429496 into Memory Address 4, then read it
        address    <= x"00000004";
        write_data <= std_logic_vector(to_unsigned(429496, 32));
        mem_write  <= '1';
        mem_read   <= '0';
        wait for 10 ns;

        mem_write  <= '0';
        mem_read   <= '1';
        wait for 10 ns;
        assert read_data = std_logic_vector(to_unsigned(429496, 32))
            report "Task 1(ii) readback mismatch at address 4"
            severity error;

        report "Data memory task checks completed successfully." severity note;

        wait;
    end process;

end Behavioral;

vhdl/simulations/data_memory_tb.vcd
$date
  Thu Apr 02 01:14:26 2026
$end
$version
  GHDL v0
$end
$timescale
  1 fs
$end
$scope module standard $end
$upscope $end
$scope module std_logic_1164 $end
$upscope $end
$scope module numeric_std $end
$upscope $end
$scope module data_memory_tb $end
$var reg 1 ! clk $end
$var reg 1 " mem_write $end
$var reg 1 # mem_read $end
$var reg 32 $ address[31:0] $end
$var reg 32 % write_data[31:0] $end
$var reg 32 & read_data[31:0] $end
$scope module uut $end
$var reg 1 ' clk $end
$var reg 1 ( mem_write $end
$var reg 1 ) mem_read $end
$var reg 32 * address[31:0] $end
$var reg 32 + write_data[31:0] $end
$var reg 32 , read_data[31:0] $end
$comment memory is not handled $end
$upscope $end
$upscope $end
$enddefinitions $end
#0
0!
1"
0#
b00000000000000000000000000000010 $
b00000000000000000000010000000000 %
bUUUUUUUUUUUUUUUUUUUUUUUUUUUUUUUU &
0'
1(
0)
b00000000000000000000000000000010 *
b00000000000000000000010000000000 +
bUUUUUUUUUUUUUUUUUUUUUUUUUUUUUUUU ,
#5000000
1!
b00000000000000000000000000000000 &
1'
b00000000000000000000000000000000 ,
#10000000
0!
0"
1#
0'
0(
1)
#15000000
1!
b00000000000000000000010000000000 &
1'
b00000000000000000000010000000000 ,
#20000000
0!
1"
0#
b00000000000000000000000000000100 $
b00000000000001101000110110111000 %
0'
1(
0)
b00000000000000000000000000000100 *
b00000000000001101000110110111000 +
#25000000
1!
b00000000000000000000000000000000 &
1'
b00000000000000000000000000000000 ,
#30000000
0!
0"
1#
0'
0(
1)
#35000000
1!
b00000000000001101000110110111000 &
1'
b00000000000001101000110110111000 ,
