vhdl/src/register_file.vhd
library IEEE;
use IEEE.STD_LOGIC_1164.ALL;
use IEEE.NUMERIC_STD.ALL;

entity Register_File_VHDL is
    Port (
        clk             : in  STD_LOGIC;
        rst             : in  STD_LOGIC;
        reg_write_en    : in  STD_LOGIC;
        reg_write_dest  : in  STD_LOGIC_VECTOR(2 downto 0);
        reg_write_data  : in  STD_LOGIC_VECTOR(31 downto 0);
        reg_read_addr_1 : in  STD_LOGIC_VECTOR(2 downto 0);
        reg_read_addr_2 : in  STD_LOGIC_VECTOR(2 downto 0);
        reg_read_data_1 : out STD_LOGIC_VECTOR(31 downto 0);
        reg_read_data_2 : out STD_LOGIC_VECTOR(31 downto 0)
    );
end Register_File_VHDL;

architecture Behavioral of Register_File_VHDL is
    type reg_array is array (0 to 7) of STD_LOGIC_VECTOR(31 downto 0);
    signal regs : reg_array := (
        0 => x"00000001",
        1 => x"00000002",
        2 => x"00000003",
        3 => x"00000004",
        4 => x"00000005",
        5 => x"00000006",
        6 => x"00000007",
        7 => x"00000008"
    );
begin

    process(clk, rst)
    begin
        if rst = '1' then
            regs <= (
                0 => x"00000001",
                1 => x"00000002",
                2 => x"00000003",
                3 => x"00000004",
                4 => x"00000005",
                5 => x"00000006",
                6 => x"00000007",
                7 => x"00000008"
            );
        elsif rising_edge(clk) then
            if reg_write_en = '1' and reg_write_dest /= "000" then
                regs(to_integer(unsigned(reg_write_dest))) <= reg_write_data;
            end if;
        end if;
    end process;

    reg_read_data_1 <= regs(to_integer(unsigned(reg_read_addr_1))) when reg_read_addr_1 /= "000" else x"00000000";
    reg_read_data_2 <= regs(to_integer(unsigned(reg_read_addr_2))) when reg_read_addr_2 /= "000" else x"00000000";

end Behavioral;

vhdl/testbench/register_file_tb.vhd
library IEEE;
use IEEE.STD_LOGIC_1164.ALL;
use IEEE.NUMERIC_STD.ALL;

entity Register_File_TB is
end Register_File_TB;

architecture Behavioral of Register_File_TB is

    component Register_File_VHDL
        Port (
            clk             : in  STD_LOGIC;
            rst             : in  STD_LOGIC;
            reg_write_en    : in  STD_LOGIC;
            reg_write_dest  : in  STD_LOGIC_VECTOR(2 downto 0);
            reg_write_data  : in  STD_LOGIC_VECTOR(31 downto 0);
            reg_read_addr_1 : in  STD_LOGIC_VECTOR(2 downto 0);
            reg_read_addr_2 : in  STD_LOGIC_VECTOR(2 downto 0);
            reg_read_data_1 : out STD_LOGIC_VECTOR(31 downto 0);
            reg_read_data_2 : out STD_LOGIC_VECTOR(31 downto 0)
        );
    end component;

    signal clk             : STD_LOGIC := '0';
    signal rst             : STD_LOGIC := '1';
    signal reg_write_en    : STD_LOGIC := '0';
    signal reg_write_dest  : STD_LOGIC_VECTOR(2 downto 0) := (others => '0');
    signal reg_write_data  : STD_LOGIC_VECTOR(31 downto 0) := (others => '0');
    signal reg_read_addr_1 : STD_LOGIC_VECTOR(2 downto 0) := (others => '0');
    signal reg_read_addr_2 : STD_LOGIC_VECTOR(2 downto 0) := (others => '0');
    signal reg_read_data_1 : STD_LOGIC_VECTOR(31 downto 0);
    signal reg_read_data_2 : STD_LOGIC_VECTOR(31 downto 0);

begin

    UUT: Register_File_VHDL
        port map (
            clk => clk,
            rst => rst,
            reg_write_en => reg_write_en,
            reg_write_dest => reg_write_dest,
            reg_write_data => reg_write_data,
            reg_read_addr_1 => reg_read_addr_1,
            reg_read_addr_2 => reg_read_addr_2,
            reg_read_data_1 => reg_read_data_1,
            reg_read_data_2 => reg_read_data_2
        );

    clk_process: process
    begin
        while true loop
            clk <= '0';
            wait for 5 ns;
            clk <= '1';
            wait for 5 ns;
        end loop;
    end process;

    stim_proc: process
    begin
        wait for 10 ns;
        rst <= '0';
        wait for 1 ns;

        reg_read_addr_1 <= "001";
        reg_read_addr_2 <= "011";
        wait for 5 ns;
        assert reg_read_data_1 = x"00000002" and reg_read_data_2 = x"00000004"
            report "Reset values for registers 1 and 3 are incorrect"
            severity error;

        -- Task 3(i): write the required values.
        reg_write_en <= '1';
        reg_write_dest <= "001";
        reg_write_data <= std_logic_vector(to_unsigned(1934858, 32));
        wait for 10 ns;

        reg_write_en <= '1';
        reg_write_dest <= "011";
        reg_write_data <= std_logic_vector(to_unsigned(8558447, 32));
        wait for 10 ns;

        reg_write_en <= '1';
        reg_write_dest <= "101";
        reg_write_data <= std_logic_vector(to_unsigned(203848544, 32));
        wait for 10 ns;

        reg_write_en <= '1';
        reg_write_dest <= "111";
        reg_write_data <= std_logic_vector(to_unsigned(20670420, 32));
        wait for 10 ns;

        reg_write_en <= '0';

        -- Task 3(ii): read the values back.
        reg_read_addr_1 <= "001";
        reg_read_addr_2 <= "011";
        wait for 10 ns;
        assert reg_read_data_1 = std_logic_vector(to_unsigned(1934858, 32))
            report "Register 1 readback mismatch"
            severity error;
        assert reg_read_data_2 = std_logic_vector(to_unsigned(8558447, 32))
            report "Register 3 readback mismatch"
            severity error;

        reg_read_addr_1 <= "101";
        reg_read_addr_2 <= "111";
        wait for 10 ns;
        assert reg_read_data_1 = std_logic_vector(to_unsigned(203848544, 32))
            report "Register 5 readback mismatch"
            severity error;
        assert reg_read_data_2 = std_logic_vector(to_unsigned(20670420, 32))
            report "Register 7 readback mismatch"
            severity error;

        reg_read_addr_1 <= "000";
        wait for 10 ns;
        assert reg_read_data_1 = x"00000000"
            report "Register 0 should read as zero"
            severity error;

        report "Register file checks completed successfully." severity note;

        wait;
    end process;

end Behavioral;

vhdl/simulations/register_file_tb.vcd
$date
  Thu Apr 02 01:20:40 2026
$end
$version
  GHDL v0
$end
$timescale
  1 fs
$end
$scope module standard $end
$upscope $end
$scope module std_logic_1164 $end
$upscope $end
$scope module numeric_std $end
$upscope $end
$scope module register_file_tb $end
$var reg 1 ! clk $end
$var reg 1 " rst $end
$var reg 1 # reg_write_en $end
$var reg 3 $ reg_write_dest[2:0] $end
$var reg 32 % reg_write_data[31:0] $end
$var reg 3 & reg_read_addr_1[2:0] $end
$var reg 3 ' reg_read_addr_2[2:0] $end
$var reg 32 ( reg_read_data_1[31:0] $end
$var reg 32 ) reg_read_data_2[31:0] $end
$scope module uut $end
$var reg 1 * clk $end
$var reg 1 + rst $end
$var reg 1 , reg_write_en $end
$var reg 3 - reg_write_dest[2:0] $end
$var reg 32 . reg_write_data[31:0] $end
$var reg 3 / reg_read_addr_1[2:0] $end
$var reg 3 0 reg_read_addr_2[2:0] $end
$var reg 32 1 reg_read_data_1[31:0] $end
$var reg 32 2 reg_read_data_2[31:0] $end
$comment regs is not handled $end
$upscope $end
$upscope $end
$enddefinitions $end
#0
0!
1"
0#
b000 $
b00000000000000000000000000000000 %
b000 &
b000 '
b00000000000000000000000000000000 (
b00000000000000000000000000000000 )
0*
1+
0,
b000 -
b00000000000000000000000000000000 .
b000 /
b000 0
b00000000000000000000000000000000 1
b00000000000000000000000000000000 2
#5000000
1!
1*
#10000000
0!
0"
0*
0+
#11000000
b001 &
b011 '
b00000000000000000000000000000010 (
b00000000000000000000000000000100 )
b001 /
b011 0
b00000000000000000000000000000010 1
b00000000000000000000000000000100 2
#15000000
1!
1*
#16000000
1#
b001 $
b00000000000111011000011000001010 %
1,
b001 -
b00000000000111011000011000001010 .
#20000000
0!
0*
#25000000
1!
b00000000000111011000011000001010 (
1*
b00000000000111011000011000001010 1
#26000000
b011 $
b00000000100000101001011101101111 %
b011 -
b00000000100000101001011101101111 .
#30000000
0!
0*
#35000000
1!
b00000000100000101001011101101111 )
1*
b00000000100000101001011101101111 2
#36000000
b101 $
b00001100001001100111101101100000 %
b101 -
b00001100001001100111101101100000 .
#40000000
0!
0*
#45000000
1!
1*
#46000000
b111 $
b00000001001110110110011111010100 %
b111 -
b00000001001110110110011111010100 .
#50000000
0!
0*
#55000000
1!
1*
#56000000
0#
0,
#60000000
0!
0*
#65000000
1!
1*
#66000000
b101 &
b111 '
b00001100001001100111101101100000 (
b00000001001110110110011111010100 )
b101 /
b111 0
b00001100001001100111101101100000 1
b00000001001110110110011111010100 2
#70000000
0!
0*
#75000000
1!
1*
#76000000
b000 &
b00000000000000000000000000000000 (
b000 /
b00000000000000000000000000000000 1
